{
    "id": "000000219861",
    "image": "coco/train2017/000000219861.jpg",
    "conversations_v0": [
        {
            "image_position": "single",
            "objects": [],
            "skills": [],
            "format": "Norm",
            "question": "What is the general state of the living room in the image?",
            "steps": [],
            "answer": "The living room in the image appears to be cluttered and messy, with lots of furniture and various items scattered throughout the space."
        },
        {
            "image_position": "single",
            "objects": [],
            "skills": [],
            "format": "Norm",
            "question": "Is there a laptop visible in the living room?",
            "steps": [],
            "answer": "Yes, there is a laptop visible in the rather cluttered living room."
        },
        {
            "image_position": "single",
            "objects": [],
            "skills": [],
            "format": "Norm",
            "question": "Describe the furniture in the living room.",
            "steps": [],
            "answer": "The living room contains large furniture, likely including chairs, an entertainment center, and possibly other furnishings such as a sofa or coffee table. The furniture seems to be contributing to the cluttered appearance of the room."
        },
        {
            "image_position": "single",
            "objects": [],
            "skills": [],
            "format": "Norm",
            "question": "What could be some reasons for the messy state of the living room?",
            "steps": [],
            "answer": "There could be a variety of reasons for the messy state of the living room:\n\n1. Space constraints: The living room may be relatively small, causing the large furniture to take up a significant portion of the available space. This can make it difficult to keep the room organized and prevent it from looking cluttered.\n\n2. Lack of organization: The homeowners may not have a proper method of organizing their belongings or adequate storage solutions, leading to a buildup of clutter in the room. Disorganized placement of items such as magazines, remote controls, chargers, or decorative pieces can contribute to the room's chaotic appearance.\n\n3. Work-from-home situation: The presence of a laptop in the living room could indicate that a resident works or studies from the comfort of the living area. As a result, this person might utilize the space throughout the day, leading to a messy environment with office supplies or personal items scattered around.\n\n4. Busy lifestyle: The residents of the household may have a hectic lifestyle, which prevents them from dedicating time and effort to tidy up the living room regularly. Balancing work, social, and family commitments can sometimes result in a temporary or prolonged state of disorganization in one's living space.\n\n5. Personal preference: Some individuals may find comfort in a more cluttered environment, lacking motivation or desire to maintain a pristine living area.\n\nUltimately, addressing the clutter issue would involve understanding the reasons behind it, providing appropriate storage solutions, and encouraging consistent organization habits."
        }
    ],
    "conversations_v1": [],
    "conversations_v2": [],
    "topic_name": [],
    "caption": [
        {
            "from": "human",
            "value": "<image>\nWhat do you see happening in this image?"
        },
        {
            "from": "gpt",
            "value": "This image captures a scene of a living room that tells a story of a vibrant and eclectic lifestyle. The room is dominated by warm tones, with the red walls serving as a bold backdrop to the array of objects scattered around.\n\nOn the left, a wooden bookshelf stands tall, housing a blue lamp and a yellow vase on its top shelf. The lamp, with its cool blue hue, provides a stark contrast to the warm red walls. The yellow vase adds a pop of color, hinting at an artistic flair.\n\nAdjacent to the bookshelf is an armchair, its leopard print pattern exuding an air of boldness and individuality. A pink blanket is casually draped over it, adding a touch of softness to the otherwise fierce print. A white laptop rests on the chair, suggesting that this corner might serve as a cozy workspace.\n\nIn front of the armchair, a red wicker basket holds a pile of papers and a white phone. The basket's location suggests it's used for handy storage or perhaps as an 'in-tray' for ongoing work.\n\nOn the right side of the room, a wooden TV stand holds a black TV and a white DVD player. The presence of these electronics indicates this area is used for entertainment and relaxation.\n\nNext to the TV stand is a blue stool, standing on top of a red and white rug. The stool's vibrant blue color complements the red rug underneath it, creating an interesting visual contrast.\n\nThe hardwood floor ties the room together with its natural tones and texture. It provides a solid foundation for the various objects in the room, each telling their own story about the person who lives here."
        }
    ],
    "det": [
        {
            "label": "tv",
            "bbox": [
                0.64224,
                0.10473309608540925,
                0.7277,
                0.2708540925266904
            ]
        },
        {
            "label": "bottle",
            "bbox": [
                0.3609,
                0.24320284697508898,
                0.38258,
                0.3018149466192171
            ]
        },
        {
            "label": "bottle",
            "bbox": [
                0.36736,
                0.28612099644128114,
                0.3827,
                0.3754092526690392
            ]
        },
        {
            "label": "chair",
            "bbox": [
                0.19216,
                0.28985765124555163,
                0.52638,
                0.9855160142348754
            ]
        },
        {
            "label": "couch",
            "bbox": [
                0.08926,
                0.14113879003558719,
                0.41237999999999997,
                0.3917081850533808
            ]
        },
        {
            "label": "laptop",
            "bbox": [
                0.39542,
                0.21565836298932384,
                0.49670000000000003,
                0.3819928825622776
            ]
        },
        {
            "label": "remote",
            "bbox": [
                0.5177999999999999,
                0.5006405693950178,
                0.57014,
                0.578896797153025
            ]
        },
        {
            "label": "book",
            "bbox": [
                0.49134,
                0.6087544483985765,
                0.6316799999999999,
                0.7145907473309608
            ]
        },
        {
            "label": "book",
            "bbox": [
                0.0682,
                0.6292170818505338,
                0.1705,
                0.8
            ]
        },
        {
            "label": "book",
            "bbox": [
                0.4938,
                0.5597153024911032,
                0.6403,
                0.6810320284697509
            ]
        },
        {
            "label": "vase",
            "bbox": [
                0.1097,
                0.425729537366548,
                0.17136,
                0.5370106761565836
            ]
        },
        {
            "label": "person",
            "bbox": [
                0.46632,
                0.00035587188612099647,
                0.50244,
                0.09854092526690392
            ]
        },
        {
            "label": "bowl",
            "bbox": [
                0.7974199999999999,
                0.6245907473309609,
                0.8598,
                0.7013879003558718
            ]
        },
        {
            "label": "potted plant",
            "bbox": [
                0.09322,
                0.38576512455516015,
                0.17434,
                0.5211387900355872
            ]
        },
        {
            "label": "microwave",
            "bbox": [
                0.87324,
                0.3244483985765125,
                0.97688,
                0.4906405693950178
            ]
        },
        {
            "label": "book",
            "bbox": [
                0.48594,
                0.5116014234875444,
                0.5891799999999999,
                0.6068683274021353
            ]
        },
        {
            "label": "book",
            "bbox": [
                0.49438,
                0.6402846975088967,
                0.6308199999999999,
                0.7465480427046263
            ]
        },
        {
            "label": "bowl",
            "bbox": [
                0.8348,
                0.6959430604982206,
                0.9205599999999999,
                0.7717081850533808
            ]
        },
        {
            "label": "bowl",
            "bbox": [
                0.77262,
                0.5848754448398576,
                0.84058,
                0.6387188612099644
            ]
        }
    ],
    "hash_id": "144_coco_train2017_000000219861.jpg"
}