{
    "id": "000000045425",
    "image": "coco/train2017/000000045425.jpg",
    "conversations_v0": [
        {
            "image_position": "single",
            "objects": [],
            "skills": [],
            "format": "Norm",
            "question": "What could the woman be thinking about while gazing skyward?",
            "steps": [],
            "answer": "The woman lying on the bed gazing skyward could be thinking about various things such as reflecting on her day, making plans for the future, daydreaming, or even trying to fall asleep. People often look towards the ceiling or sky when deep in thought or lost in their imaginations. It is not possible to determine the exact content of her thoughts solely from the visual image, but her posture and gaze suggest a relaxed and contemplative state of mind."
        }
    ],
    "conversations_v1": [],
    "conversations_v2": [],
    "topic_name": [],
    "caption": [
        {
            "from": "human",
            "value": "Can you describe the main features of this image for me?\n<image>"
        },
        {
            "from": "gpt",
            "value": "This is a black and white photograph capturing a moment of tranquility in a bedroom. The main subject is a young woman, lying on her stomach on an unmade bed. Her head is resting on her hands, and she's looking directly at the camera, creating an intimate connection with the viewer.\n\nThe bed, the central piece of furniture in the room, is covered with rumpled sheets, adding a sense of casualness to the scene. Scattered around the room are various objects that give us a glimpse into the woman's life - a dresser and a nightstand, suggesting this is her personal space, and a pile of books, hinting at her interests or hobbies.\n\nThe photograph is taken from a high angle, looking down on the woman and the bed. This perspective gives us a comprehensive view of the room while also creating a sense of depth in the image.\n\nPlease note that as this is a black and white photo, specific colors of objects cannot be determined. However, the use of monochrome adds a timeless quality to the image."
        }
    ],
    "det": [
        {
            "label": "bed",
            "bbox": [
                0.006875000000000001,
                0.033698979591836736,
                1.0,
                0.9955102040816325
            ]
        },
        {
            "label": "person",
            "bbox": [
                0.42557812500000003,
                0.3278061224489796,
                0.9395468749999999,
                0.8567857142857144
            ]
        }
    ],
    "hash_id": "375_coco_train2017_000000045425.jpg"
}