{
    "id": "37755",
    "image": "tabmwp/tables/37755.png",
    "conversations_v0": [
        {
            "image_position": "single",
            "objects": [],
            "skills": [],
            "format": "Norm",
            "question": "How much money does Farid need to buy a box of envelopes and a pencil sharpener?",
            "steps": [],
            "answer": "Add the price of a box of envelopes and the price of a pencil sharpener:\n\n$0.95 + $0.32 = $1.27\n\nFarid needs $1.27."
        }
    ],
    "conversations_v1": [],
    "topic_name": [],
    "caption": [],
    "det": [],
    "hash_id": "1463_tabmwp_tables_37755.png"
}