{
    "id": "000000089298",
    "image": "coco/train2017/000000089298.jpg",
    "conversations_v0": [
        {
            "image_position": "single",
            "objects": [],
            "skills": [],
            "format": "Norm",
            "question": "What is the man wearing in the image?",
            "steps": [],
            "answer": "The man in the image is wearing a bathing suit or swim shorts, and he has no shirt on."
        },
        {
            "image_position": "single",
            "objects": [],
            "skills": [],
            "format": "Norm",
            "question": "Where is the man standing?",
            "steps": [],
            "answer": "The man is standing outside in a park, specifically on a towel and in the grass."
        },
        {
            "image_position": "single",
            "objects": [],
            "skills": [],
            "format": "Norm",
            "question": "What is the man doing in the image?",
            "steps": [],
            "answer": "The man is talking on his cell phone while standing in the park."
        },
        {
            "image_position": "single",
            "objects": [],
            "skills": [],
            "format": "Norm",
            "question": "Can you describe the overall atmosphere of the image? Is it a sunny day or a cloudy day?",
            "steps": [],
            "answer": "While I can't provide a direct observation of the weather in the image, the fact that the man is wearing a bathing suit and is shirtless might suggest that it is a warm and possibly sunny day. This would create an atmosphere conducive to outdoor activities and enjoying the park, which is consistent with the man's decision to spend time outside."
        },
        {
            "image_position": "single",
            "objects": [],
            "skills": [],
            "format": "Norm",
            "question": "Write a detailed description of the given image.",
            "steps": [],
            "answer": "The image shows a park scene where a shirtless man, possibly wearing a bathing suit, is standing in the grass and talking on his cell phone. He appears to be enjoying the outdoors while engaged in a conversation. \n\nMany people are present in this park, some sitting on benches and others standing among their fellow park-goers. There are a couple of handbags and backpacks scattered around, possibly belonging to the visitors. \n\nIn the background, a traffic light can be seen on the edge of the park, and a car is positioned further away, indicating the presence of a street nearby. Overall, this image captures a lively park setting where people are spending their leisure time."
        },
        {
            "image_position": "single",
            "objects": [],
            "skills": [],
            "format": "Norm",
            "question": "How can one infer that the shirtless man could be engaging in a recreational activity at the park?",
            "steps": [],
            "answer": "One can infer that the shirtless man is engaging in a recreational activity at the park based on the visual cues present in the image. In the image, the man has no shirt on, is wearing swim shorts, and is standing on a towel. This particular outfit suggests that he is at the park for a leisurely activity, possibly to sunbathe or participate in water games. Additionally, there are other people around the park, which emphasizes that it could be a popular spot for people to relax and unwind. The presence of benches and backpacks also supports the idea that this is a recreational environment. Another clue is that the man is talking on his cell phone, which could imply he is not currently engaged in physical exercise or other activities that would require his uninterrupted focus."
        }
    ],
    "caption": [
        {
            "from": "human",
            "value": "Analyze the image in a comprehensive and detailed manner.\n<image>"
        },
        {
            "from": "gpt",
            "value": "In the heart of a lively park, a man stands out, engrossed in a conversation on his cell phone. His attire is casual, with red shorts and a black baseball cap adorning him, while his shirtless torso basks in the sunlight. A black backpack and a white towel lie next to him on the verdant grass, perhaps indicating a workout session or a day out in the park.\n\nThe park itself is alive with activity. In the background, several people can be seen enjoying their time, comfortably seated on benches. A car parked on the street adds to the everyday hustle and bustle of this scene.\n\nThe image captures a slice of life, presenting a moment of solitude amidst the buzz of communal activity. The man, despite being in the midst of it all, seems to be in his own world, adding a layer of depth to this everyday scenario."
        }
    ],
    "det": [
        {
            "label": "cell phone",
            "bbox": [
                0.4398298676748582,
                0.2324375,
                0.4642722117202268,
                0.2554375
            ]
        },
        {
            "label": "car",
            "bbox": [
                0.5862759924385633,
                0.458421875,
                0.9615500945179584,
                0.59684375
            ]
        },
        {
            "label": "traffic light",
            "bbox": [
                0.9351606805293006,
                0.28518750000000004,
                0.9918714555765596,
                0.395046875
            ]
        },
        {
            "label": "person",
            "bbox": [
                0.8785066162570889,
                0.56684375,
                1.0,
                0.8231093749999999
            ]
        },
        {
            "label": "person",
            "bbox": [
                0.03510396975425331,
                0.502375,
                0.0913421550094518,
                0.5975625
            ]
        },
        {
            "label": "person",
            "bbox": [
                0.13398865784499053,
                0.5246875,
                0.16735349716446124,
                0.556203125
            ]
        },
        {
            "label": "person",
            "bbox": [
                0.24829867674858222,
                0.524671875,
                0.29207939508506614,
                0.5978125000000001
            ]
        },
        {
            "label": "bench",
            "bbox": [
                0.0018525519848771267,
                0.581828125,
                0.4241587901701323,
                0.81428125
            ]
        },
        {
            "label": "bench",
            "bbox": [
                0.6084877126654064,
                0.589390625,
                0.9731758034026464,
                0.8149218749999999
            ]
        },
        {
            "label": "backpack",
            "bbox": [
                0.21158790170132327,
                0.824359375,
                0.46928166351606804,
                0.9723437500000001
            ]
        },
        {
            "label": "backpack",
            "bbox": [
                0.0687523629489603,
                0.527828125,
                0.09103969754253308,
                0.56725
            ]
        },
        {
            "label": "person",
            "bbox": [
                0.30892249527410204,
                0.542265625,
                0.3235349716446124,
                0.5571718750000001
            ]
        },
        {
            "label": "person",
            "bbox": [
                0.3991493383742911,
                0.555640625,
                0.645633270321361,
                0.82465625
            ]
        },
        {
            "label": "handbag",
            "bbox": [
                0.299640831758034,
                0.6272031250000001,
                0.39103969754253304,
                0.71115625
            ]
        },
        {
            "label": "handbag",
            "bbox": [
                0.35765595463137995,
                0.657921875,
                0.42185255198487714,
                0.7145625
            ]
        },
        {
            "label": "traffic light",
            "bbox": [
                0.8948582230623818,
                0.346609375,
                0.9315879017013232,
                0.432421875
            ]
        },
        {
            "label": "person",
            "bbox": [
                0.4148015122873346,
                0.1350625,
                0.6379017013232514,
                0.9714218750000001
            ]
        },
        {
            "label": "person",
            "bbox": [
                0.6080529300567108,
                0.49053125,
                0.6460302457466919,
                0.5492343749999999
            ]
        },
        {
            "label": "person",
            "bbox": [
                0.7187712665406427,
                0.46890625,
                0.7885255198487713,
                0.540140625
            ]
        }
    ],
    "hash_id": "335_coco_train2017_000000089298.jpg"
}